parts2kicad/__init__.py
parts2kicad/fprints.py
parts2kicad/main.py
parts2kicad/models.py
parts2kicad/sexp.py
parts2kicad/symbols.py
parts2kicad/term.py
parts2kicad/util.py
parts2kicad-0.1.2.dist-info/WHEEL
parts2kicad-0.1.2.dist-info/entry_points.txt
parts2kicad-0.1.2.dist-info/METADATA
parts2kicad-0.1.2.dist-info/RECORD
