Metadata-Version: 2.3
Name: parts2kicad
Version: 0.1.2
Summary: Integrate (add) symbols, footprints and 3D models from a SamacSys Partlib zip archive (as downloaded for instance from Mouser or Farnell) into local KiCad libraries quickly and without additional steps
Requires-Dist: importlib>=1.0.4
Requires-Dist: uv-build>=0.9.13
Requires-Dist: colorama>=0.4.6
Requires-Python: >=3.8
